Metadata-Version: 2.1
Name: tensorrt_cu11_bindings
Version: 10.13.0.35
Summary: A high performance deep learning inference library
Home-page: https://github.com/nvidia/tensorrt
Download-URL: https://developer.nvidia.com/tensorrt
Author: NVIDIA Corporation
License: Proprietary
Keywords: nvidia tensorrt deeplearning inference
Classifier: License :: Other/Proprietary License
Classifier: Intended Audience :: Developers
Classifier: Programming Language :: Python :: 3
License-File: LICENSE.txt
Provides-Extra: numpy
Requires-Dist: numpy ; extra == 'numpy'
